dworshak/__init__.py
dworshak/cli.py
dworshak/paths.py
dworshak/services.py
dworshak/core/__init__.py
dworshak/core/bootstrap.py
dworshak/core/security.py
dworshak/core/vault.py
dworshak-0.1.2.dist-info/licenses/LICENSE
dworshak-0.1.2.dist-info/METADATA
dworshak-0.1.2.dist-info/WHEEL
dworshak-0.1.2.dist-info/entry_points.txt
dworshak-0.1.2.dist-info/top_level.txt
dworshak-0.1.2.dist-info/RECORD
