Metadata-Version: 2.4
Name: dworshak
Version: 0.1.2
Summary: Manage local, encrypted credentials. The **dworshak* CLI leverages openssl, sqlite3, and cryptography.
Requires-Python: >=3.12
License-File: LICENSE
Requires-Dist: cryptography>=46.0.3
Requires-Dist: typer>=0.21.0
Requires-Dist: rich>=13.0.0
Dynamic: license-file
